{"location":{"name":"Calcutta","region":"West Bengal","country":"India","lat":22.57,"lon":88.37,"tz_id":"Asia/Kolkata","localtime_epoch":1764963318,"localtime":"2025-12-06 01:05"},"current":{"last_updated_epoch":1764963000,"last_updated":"2025-12-06 01:00","temp_c":18.2,"temp_f":64.8,"is_day":0,"condition":{"text":"Mist","icon":"//cdn.weatherapi.com/weather/64x64/night/143.png","code":1030},"wind_mph":7.8,"wind_kph":12.6,"wind_degree":347,"wind_dir":"NNW","pressure_mb":1017.0,"pressure_in":30.03,"precip_mm":0.0,"precip_in":0.0,"humidity":56,"cloud":0,"feelslike_c":18.2,"feelslike_f":64.8,"windchill_c":17.1,"windchill_f":62.7,"heatindex_c":17.1,"heatindex_f":62.7,"dewpoint_c":0.4,"dewpoint_f":32.7,"vis_km":2.8,"vis_miles":1.0,"uv":0.0,"gust_mph":16.4,"gust_kph":26.5,"air_quality":{"co":993.85,"no2":43.15,"o3":62.0,"so2":38.75,"pm2_5":131.25,"pm10":133.05,"us-epa-index":4,"gb-defra-index":10}}}