{"location":{"name":"Calcutta","region":"West Bengal","country":"India","lat":22.57,"lon":88.37,"tz_id":"Asia/Kolkata","localtime_epoch":1767102061,"localtime":"2025-12-30 19:11"},"current":{"last_updated_epoch":1767101400,"last_updated":"2025-12-30 19:00","temp_c":15.1,"temp_f":59.2,"is_day":0,"condition":{"text":"Mist","icon":"//cdn.weatherapi.com/weather/64x64/night/143.png","code":1030},"wind_mph":2.5,"wind_kph":4.0,"wind_degree":332,"wind_dir":"NNW","pressure_mb":1013.0,"pressure_in":29.91,"precip_mm":0.0,"precip_in":0.0,"humidity":77,"cloud":0,"feelslike_c":15.1,"feelslike_f":59.2,"windchill_c":20.5,"windchill_f":68.9,"heatindex_c":20.5,"heatindex_f":68.9,"dewpoint_c":0.0,"dewpoint_f":32.0,"vis_km":2.8,"vis_miles":1.0,"uv":0.0,"gust_mph":5.2,"gust_kph":8.3,"air_quality":{"co":675.85,"no2":6.85,"o3":227.0,"so2":34.75,"pm2_5":99.35,"pm10":101.85,"us-epa-index":4,"gb-defra-index":10}}}