{"location":{"name":"Calcutta","region":"West Bengal","country":"India","lat":22.57,"lon":88.37,"tz_id":"Asia/Kolkata","localtime_epoch":1765341564,"localtime":"2025-12-10 10:09"},"current":{"last_updated_epoch":1765341000,"last_updated":"2025-12-10 10:00","temp_c":21.1,"temp_f":70.0,"is_day":1,"condition":{"text":"Mist","icon":"//cdn.weatherapi.com/weather/64x64/day/143.png","code":1030},"wind_mph":8.9,"wind_kph":14.4,"wind_degree":353,"wind_dir":"N","pressure_mb":1019.0,"pressure_in":30.09,"precip_mm":0.0,"precip_in":0.0,"humidity":64,"cloud":25,"feelslike_c":21.1,"feelslike_f":70.0,"windchill_c":25.3,"windchill_f":77.5,"heatindex_c":25.1,"heatindex_f":77.1,"dewpoint_c":7.7,"dewpoint_f":45.9,"vis_km":1.1,"vis_miles":0.0,"uv":4.8,"gust_mph":10.3,"gust_kph":16.6,"air_quality":{"co":1293.85,"no2":23.15,"o3":61.0,"so2":24.75,"pm2_5":135.85,"pm10":137.25,"us-epa-index":4,"gb-defra-index":10}}}