{"location":{"name":"Calcutta","region":"West Bengal","country":"India","lat":22.57,"lon":88.37,"tz_id":"Asia/Kolkata","localtime_epoch":1763930360,"localtime":"2025-11-24 02:09"},"current":{"last_updated_epoch":1763929800,"last_updated":"2025-11-24 02:00","temp_c":20.2,"temp_f":68.4,"is_day":0,"condition":{"text":"Mist","icon":"//cdn.weatherapi.com/weather/64x64/night/143.png","code":1030},"wind_mph":5.6,"wind_kph":9.0,"wind_degree":34,"wind_dir":"NE","pressure_mb":1015.0,"pressure_in":29.97,"precip_mm":0.0,"precip_in":0.0,"humidity":83,"cloud":0,"feelslike_c":20.2,"feelslike_f":68.4,"windchill_c":19.7,"windchill_f":67.4,"heatindex_c":19.7,"heatindex_f":67.4,"dewpoint_c":9.8,"dewpoint_f":49.6,"vis_km":2.4,"vis_miles":1.0,"uv":0.0,"gust_mph":11.7,"gust_kph":18.9,"air_quality":{"co":1542.85,"no2":67.75,"o3":67.0,"so2":58.95,"pm2_5":181.05,"pm10":184.75,"us-epa-index":5,"gb-defra-index":10}}}