{"location":{"name":"Calcutta","region":"West Bengal","country":"India","lat":22.57,"lon":88.37,"tz_id":"Asia/Kolkata","localtime_epoch":1764804980,"localtime":"2025-12-04 05:06"},"current":{"last_updated_epoch":1764804600,"last_updated":"2025-12-04 05:00","temp_c":17.3,"temp_f":63.1,"is_day":0,"condition":{"text":"Mist","icon":"//cdn.weatherapi.com/weather/64x64/night/143.png","code":1030},"wind_mph":7.2,"wind_kph":11.5,"wind_degree":350,"wind_dir":"N","pressure_mb":1015.0,"pressure_in":29.97,"precip_mm":0.0,"precip_in":0.0,"humidity":83,"cloud":0,"feelslike_c":17.3,"feelslike_f":63.1,"windchill_c":16.2,"windchill_f":61.2,"heatindex_c":16.2,"heatindex_f":61.2,"dewpoint_c":0.7,"dewpoint_f":33.3,"vis_km":2.2,"vis_miles":1.0,"uv":0.0,"gust_mph":15.0,"gust_kph":24.2,"air_quality":{"co":1246.85,"no2":58.55,"o3":40.0,"so2":49.65,"pm2_5":192.75,"pm10":193.65,"us-epa-index":5,"gb-defra-index":10}}}