{"location":{"name":"Calcutta","region":"West Bengal","country":"India","lat":22.57,"lon":88.37,"tz_id":"Asia/Kolkata","localtime_epoch":1776526830,"localtime":"2026-04-18 21:10"},"current":{"last_updated_epoch":1776526200,"last_updated":"2026-04-18 21:00","temp_c":29.4,"temp_f":84.9,"is_day":0,"condition":{"text":"Mist","icon":"//cdn.weatherapi.com/weather/64x64/night/143.png","code":1030},"wind_mph":15.2,"wind_kph":24.5,"wind_degree":190,"wind_dir":"S","pressure_mb":1006.0,"pressure_in":29.71,"precip_mm":0.0,"precip_in":0.0,"humidity":84,"cloud":50,"feelslike_c":34.8,"feelslike_f":94.6,"windchill_c":28.3,"windchill_f":82.9,"heatindex_c":32.3,"heatindex_f":90.1,"dewpoint_c":23.6,"dewpoint_f":74.5,"vis_km":3.5,"vis_miles":2.0,"uv":0.0,"gust_mph":21.3,"gust_kph":34.3,"air_quality":{"co":323.85,"no2":6.85,"o3":99.0,"so2":9.55,"pm2_5":26.55,"pm10":32.35,"us-epa-index":2,"gb-defra-index":3}}}