{"location":{"name":"Calcutta","region":"West Bengal","country":"India","lat":22.57,"lon":88.37,"tz_id":"Asia/Kolkata","localtime_epoch":1761125288,"localtime":"2025-10-22 14:58"},"current":{"last_updated_epoch":1761124500,"last_updated":"2025-10-22 14:45","temp_c":33.1,"temp_f":91.6,"is_day":1,"condition":{"text":"Mist","icon":"//cdn.weatherapi.com/weather/64x64/day/143.png","code":1030},"wind_mph":6.5,"wind_kph":10.4,"wind_degree":356,"wind_dir":"N","pressure_mb":1009.0,"pressure_in":29.8,"precip_mm":0.0,"precip_in":0.0,"humidity":53,"cloud":25,"feelslike_c":34.4,"feelslike_f":93.9,"windchill_c":32.6,"windchill_f":90.7,"heatindex_c":33.6,"heatindex_f":92.6,"dewpoint_c":16.9,"dewpoint_f":62.3,"vis_km":3.5,"vis_miles":2.0,"uv":3.2,"gust_mph":8.0,"gust_kph":12.9,"air_quality":{"co":652.85,"no2":10.65,"o3":162.0,"so2":13.55,"pm2_5":44.35,"pm10":44.85,"us-epa-index":3,"gb-defra-index":5}}}