{"location":{"name":"Calcutta","region":"West Bengal","country":"India","lat":22.57,"lon":88.37,"tz_id":"Asia/Kolkata","localtime_epoch":1760585254,"localtime":"2025-10-16 08:57"},"current":{"last_updated_epoch":1760584500,"last_updated":"2025-10-16 08:45","temp_c":28.4,"temp_f":83.1,"is_day":1,"condition":{"text":"Mist","icon":"//cdn.weatherapi.com/weather/64x64/day/143.png","code":1030},"wind_mph":7.2,"wind_kph":11.5,"wind_degree":349,"wind_dir":"N","pressure_mb":1011.0,"pressure_in":29.85,"precip_mm":0.0,"precip_in":0.0,"humidity":62,"cloud":0,"feelslike_c":30.7,"feelslike_f":87.2,"windchill_c":26.3,"windchill_f":79.3,"heatindex_c":27.7,"heatindex_f":81.8,"dewpoint_c":18.6,"dewpoint_f":65.5,"vis_km":3.5,"vis_miles":2.0,"uv":2.8,"gust_mph":8.7,"gust_kph":13.9,"air_quality":{"co":827.85,"no2":26.55,"o3":51.0,"so2":30.65,"pm2_5":104.65,"pm10":110.75,"us-epa-index":4,"gb-defra-index":10}}}