{"location":{"name":"Calcutta","region":"West Bengal","country":"India","lat":22.57,"lon":88.37,"tz_id":"Asia/Kolkata","localtime_epoch":1764209800,"localtime":"2025-11-27 07:46"},"current":{"last_updated_epoch":1764209700,"last_updated":"2025-11-27 07:45","temp_c":18.1,"temp_f":64.6,"is_day":1,"condition":{"text":"Mist","icon":"//cdn.weatherapi.com/weather/64x64/day/143.png","code":1030},"wind_mph":7.8,"wind_kph":12.6,"wind_degree":8,"wind_dir":"N","pressure_mb":1017.0,"pressure_in":30.03,"precip_mm":0.0,"precip_in":0.0,"humidity":83,"cloud":25,"feelslike_c":18.1,"feelslike_f":64.6,"windchill_c":19.4,"windchill_f":67.0,"heatindex_c":19.4,"heatindex_f":67.0,"dewpoint_c":12.5,"dewpoint_f":54.4,"vis_km":1.5,"vis_miles":0.0,"uv":0.6,"gust_mph":10.8,"gust_kph":17.4,"air_quality":{"co":707.85,"no2":29.55,"o3":50.0,"so2":24.75,"pm2_5":129.85,"pm10":131.75,"us-epa-index":4,"gb-defra-index":10}}}