{"location":{"name":"Calcutta","region":"West Bengal","country":"India","lat":22.57,"lon":88.37,"tz_id":"Asia/Kolkata","localtime_epoch":1763440984,"localtime":"2025-11-18 10:13"},"current":{"last_updated_epoch":1763440200,"last_updated":"2025-11-18 10:00","temp_c":26.2,"temp_f":79.2,"is_day":1,"condition":{"text":"Mist","icon":"//cdn.weatherapi.com/weather/64x64/day/143.png","code":1030},"wind_mph":7.4,"wind_kph":11.9,"wind_degree":359,"wind_dir":"N","pressure_mb":1016.0,"pressure_in":30.0,"precip_mm":0.0,"precip_in":0.0,"humidity":54,"cloud":25,"feelslike_c":26.3,"feelslike_f":79.3,"windchill_c":26.7,"windchill_f":80.1,"heatindex_c":26.7,"heatindex_f":80.0,"dewpoint_c":12.3,"dewpoint_f":54.1,"vis_km":2.8,"vis_miles":1.0,"uv":5.7,"gust_mph":8.5,"gust_kph":13.7,"air_quality":{"co":930.85,"no2":30.45,"o3":39.0,"so2":20.05,"pm2_5":84.25,"pm10":86.25,"us-epa-index":4,"gb-defra-index":10}}}