{"location":{"name":"Bara Bazar","region":"West Bengal","country":"India","lat":22.567,"lon":88.35,"tz_id":"Asia/Kolkata","localtime_epoch":1763199378,"localtime":"2025-11-15 15:06"},"current":{"last_updated_epoch":1763199000,"last_updated":"2025-11-15 15:00","temp_c":28.1,"temp_f":82.6,"is_day":1,"condition":{"text":"Mist","icon":"//cdn.weatherapi.com/weather/64x64/day/143.png","code":1030},"wind_mph":7.6,"wind_kph":12.2,"wind_degree":348,"wind_dir":"NNW","pressure_mb":1014.0,"pressure_in":29.94,"precip_mm":0.0,"precip_in":0.0,"humidity":45,"cloud":0,"feelslike_c":27.3,"feelslike_f":81.2,"windchill_c":27.7,"windchill_f":81.9,"heatindex_c":27.0,"heatindex_f":80.6,"dewpoint_c":10.1,"dewpoint_f":50.3,"vis_km":3.5,"vis_miles":2.0,"uv":0.9,"gust_mph":10.3,"gust_kph":16.6,"air_quality":{"co":679.85,"no2":8.95,"o3":176.0,"so2":20.75,"pm2_5":77.65,"pm10":84.65,"us-epa-index":4,"gb-defra-index":10}}}