{"location":{"name":"Calcutta","region":"West Bengal","country":"India","lat":22.57,"lon":88.37,"tz_id":"Asia/Kolkata","localtime_epoch":1760943006,"localtime":"2025-10-20 12:20"},"current":{"last_updated_epoch":1760942700,"last_updated":"2025-10-20 12:15","temp_c":33.3,"temp_f":91.9,"is_day":1,"condition":{"text":"Mist","icon":"//cdn.weatherapi.com/weather/64x64/day/143.png","code":1030},"wind_mph":7.4,"wind_kph":11.9,"wind_degree":29,"wind_dir":"NNE","pressure_mb":1010.0,"pressure_in":29.83,"precip_mm":0.0,"precip_in":0.0,"humidity":53,"cloud":25,"feelslike_c":36.0,"feelslike_f":96.8,"windchill_c":32.4,"windchill_f":90.4,"heatindex_c":34.4,"heatindex_f":94.0,"dewpoint_c":18.7,"dewpoint_f":65.7,"vis_km":4.0,"vis_miles":2.0,"uv":7.1,"gust_mph":9.0,"gust_kph":14.5,"air_quality":{"co":769.85,"no2":20.05,"o3":90.0,"so2":14.15,"pm2_5":60.65,"pm10":60.95,"us-epa-index":3,"gb-defra-index":8}}}