{"location":{"name":"Calcutta","region":"West Bengal","country":"India","lat":22.57,"lon":88.37,"tz_id":"Asia/Kolkata","localtime_epoch":1777635920,"localtime":"2026-05-01 17:15"},"current":{"last_updated_epoch":1777635000,"last_updated":"2026-05-01 17:00","temp_c":29.3,"temp_f":84.7,"is_day":1,"condition":{"text":"Mist","icon":"//cdn.weatherapi.com/weather/64x64/day/143.png","code":1030},"wind_mph":16.6,"wind_kph":26.6,"wind_degree":237,"wind_dir":"WSW","pressure_mb":1003.0,"pressure_in":29.62,"precip_mm":2.5,"precip_in":0.1,"humidity":75,"cloud":50,"feelslike_c":31.9,"feelslike_f":89.4,"windchill_c":30.9,"windchill_f":87.7,"heatindex_c":35.0,"heatindex_f":95.0,"dewpoint_c":22.4,"dewpoint_f":72.3,"vis_km":4.5,"vis_miles":2.0,"uv":0.1,"gust_mph":22.0,"gust_kph":35.4,"air_quality":{"co":384.85,"no2":4.45,"o3":178.0,"so2":17.35,"pm2_5":46.45,"pm10":54.45,"us-epa-index":3,"gb-defra-index":5}}}