{"location":{"name":"Calcutta","region":"West Bengal","country":"India","lat":22.57,"lon":88.37,"tz_id":"Asia/Kolkata","localtime_epoch":1767900755,"localtime":"2026-01-09 01:02"},"current":{"last_updated_epoch":1767900600,"last_updated":"2026-01-09 01:00","temp_c":14.2,"temp_f":57.6,"is_day":0,"condition":{"text":"Mist","icon":"//cdn.weatherapi.com/weather/64x64/night/143.png","code":1030},"wind_mph":7.6,"wind_kph":12.2,"wind_degree":356,"wind_dir":"N","pressure_mb":1019.0,"pressure_in":30.09,"precip_mm":0.0,"precip_in":0.0,"humidity":82,"cloud":0,"feelslike_c":13.4,"feelslike_f":56.1,"windchill_c":13.6,"windchill_f":56.4,"heatindex_c":14.4,"heatindex_f":57.8,"dewpoint_c":0.1,"dewpoint_f":32.1,"vis_km":2.2,"vis_miles":1.0,"uv":0.0,"gust_mph":16.0,"gust_kph":25.7,"air_quality":{"co":1276.85,"no2":50.45,"o3":60.0,"so2":40.65,"pm2_5":132.65,"pm10":135.45,"us-epa-index":4,"gb-defra-index":10}}}