{"location":{"name":"Calcutta","region":"West Bengal","country":"India","lat":22.57,"lon":88.37,"tz_id":"Asia/Kolkata","localtime_epoch":1782658726,"localtime":"2026-06-28 20:28"},"current":{"last_updated_epoch":1782657900,"last_updated":"2026-06-28 20:15","temp_c":31.1,"temp_f":88.0,"is_day":0,"condition":{"text":"Moderate or heavy rain with thunder","icon":"//cdn.weatherapi.com/weather/64x64/night/389.png","code":1276},"wind_mph":14.3,"wind_kph":23.0,"wind_degree":175,"wind_dir":"S","pressure_mb":1001.0,"pressure_in":29.56,"precip_mm":0.0,"precip_in":0.0,"humidity":79,"cloud":50,"feelslike_c":41.8,"feelslike_f":107.2,"windchill_c":30.8,"windchill_f":87.5,"heatindex_c":36.5,"heatindex_f":97.7,"dewpoint_c":24.2,"dewpoint_f":75.7,"vis_km":3.5,"vis_miles":2.0,"uv":0.0,"gust_mph":19.3,"gust_kph":31.1,"will_it_rain":0,"chance_of_rain":5,"will_it_snow":0,"chance_of_snow":0,"air_quality":{"co":323.0,"no2":9.4,"o3":59.0,"so2":6.5,"pm2_5":19.9,"pm10":22.4,"us-epa-index":2,"gb-defra-index":2}}}