{"location":{"name":"Calcutta","region":"West Bengal","country":"India","lat":22.57,"lon":88.37,"tz_id":"Asia/Kolkata","localtime_epoch":1769729871,"localtime":"2026-01-30 05:07"},"current":{"last_updated_epoch":1769729400,"last_updated":"2026-01-30 05:00","temp_c":19.3,"temp_f":66.7,"is_day":0,"condition":{"text":"Mist","icon":"//cdn.weatherapi.com/weather/64x64/night/143.png","code":1030},"wind_mph":6.7,"wind_kph":10.8,"wind_degree":10,"wind_dir":"N","pressure_mb":1017.0,"pressure_in":30.03,"precip_mm":0.0,"precip_in":0.0,"humidity":73,"cloud":0,"feelslike_c":19.3,"feelslike_f":66.7,"windchill_c":18.0,"windchill_f":64.4,"heatindex_c":18.0,"heatindex_f":64.4,"dewpoint_c":8.6,"dewpoint_f":47.4,"vis_km":1.8,"vis_miles":1.0,"uv":0.0,"gust_mph":13.6,"gust_kph":21.8,"air_quality":{"co":1080.85,"no2":55.95,"o3":52.0,"so2":45.55,"pm2_5":162.95,"pm10":165.65,"us-epa-index":5,"gb-defra-index":10}}}