{"location":{"name":"Ballygunge","region":"West Bengal","country":"India","lat":22.533,"lon":88.367,"tz_id":"Asia/Kolkata","localtime_epoch":1781215733,"localtime":"2026-06-12 03:38"},"forecast":{"forecastday":[{"date":"2026-06-12","date_epoch":1781222400,"day":{"maxtemp_c":30.6,"maxtemp_f":87.1,"mintemp_c":26.4,"mintemp_f":79.5,"avgtemp_c":29.5,"avgtemp_f":85.0,"maxwind_mph":11.8,"maxwind_kph":19.0,"totalprecip_mm":4.98,"totalprecip_in":0.2,"totalsnow_cm":0.0,"avgvis_km":9.8,"avgvis_miles":6.0,"avghumidity":78,"condition":{"text":"Patchy light rain in area with thunder","icon":"//cdn.weatherapi.com/weather/64x64/day/386.png","code":1273},"uv":6.0}}]}}